airports/__init__.py
airports/admin.py
airports/apps.py
airports/models.py
airports/locale/ru/LC_MESSAGES/django.mo
airports/locale/ru/LC_MESSAGES/django.po
airports/management/__init__.py
airports/management/commands/__init__.py
airports/management/commands/airports.py
airports/migrations/0001_initial.py
airports/migrations/0002_auto_20190225_0210.py
airports/migrations/0003_auto_20190321_1026.py
airports/migrations/0004_alter_airport_id.py
airports/migrations/0005_auto_20211222_0812.py
airports/migrations/__init__.py
airports/tests/__init__.py
airports/tests/settings.py
airports/tests/test_management.py
airports/tests/test_models.py
django_airports-1.0.3.dist-info/AUTHORS.rst
django_airports-1.0.3.dist-info/LICENSE
django_airports-1.0.3.dist-info/METADATA
django_airports-1.0.3.dist-info/WHEEL
django_airports-1.0.3.dist-info/top_level.txt
django_airports-1.0.3.dist-info/RECORD
